<?xml version="1.0"?>
<!DOCTYPE hibernate-mapping PUBLIC "-//Hibernate/Hibernate Mapping DTD 3.0//EN"
"http://hibernate.sourceforge.net/hibernate-mapping-3.0.dtd">
<!-- Generated Jul 22, 2024, 10:25:21 PM by Hibernate Tools 3.5.0.Final -->
<hibernate-mapping package="in.co.rays.project_3.dto">

     <class name="LoanDTO" table="st_loan">
		<id name="id" type="java.lang.Long">
			<column name="ID" />
			<generator class="increment" />
		</id>
        <property name="loanStartDate" type="java.util.Date">
            <column name="LOANSTARTDATE" />
        </property>
        <property name="intrestRate" type="java.lang.Integer">
            <column name="INTRESTRATE" />
        </property>
        <property name="customerId" type="java.lang.String">
            <column name="CUSTOMERID" />
        </property>
        <property name="loanAmount" type="java.lang.Integer">
            <column name="LOANAMOUNT" />
        </property>
    </class>
</hibernate-mapping>
